kosmo_mcp/__init__.py
kosmo_mcp/server.py
kosmo_mcp-1.1.16.dist-info/METADATA
kosmo_mcp-1.1.16.dist-info/WHEEL
kosmo_mcp-1.1.16.dist-info/entry_points.txt
kosmo_mcp-1.1.16.dist-info/licenses/LICENSE
kosmo_mcp-1.1.16.dist-info/RECORD
