Metadata-Version: 2.4
Name: kosmo-mcp
Version: 1.1.16
Summary: KOSMO - ZOO-Certified Agentic Protocol MCP Server for Builders
Project-URL: Homepage, https://hermios.us
Project-URL: Repository, https://github.com/Open-Hermios/Kosmo
Author-email: Hermios <info@hermios.us>
License: MIT
License-File: LICENSE
Keywords: agentic,ai,kosmo,mcp,protocol,zoo
Classifier: Development Status :: 4 - Beta
Classifier: Environment :: Console
Classifier: Intended Audience :: Developers
Classifier: License :: OSI Approved :: MIT License
Classifier: Programming Language :: Python :: 3.10
Classifier: Programming Language :: Python :: 3.11
Classifier: Programming Language :: Python :: 3.12
Classifier: Topic :: Software Development :: Libraries :: Python Modules
Requires-Python: >=3.10
Requires-Dist: httpx>=0.27.0
Requires-Dist: mcp>=1.0.0
